{"a58d1695-ca8a-4b62-bf91-1016f5fbd8c6": {"id": "a58d1695-ca8a-4b62-bf91-1016f5fbd8c6", "cost": "Paid", "description": "Earners of this credential have demonstrated the skills and knowledge required to follow and apply work health and safety (WHS) / occupational health and safety (OHS) procedures when carrying out work in compliance with the relevant WHS/OHS regulations. Earners are able to identify hazards and control risks, contribute to WHS/OHS management arrangements and complete WHS/OHS records.", "global_activity_url": "https://www.bluecard.com.au", "earn_this_badge_url": null, "enable_earn_this_badge": false, "enable_detail_attribute_visibility": true, "level": "Foundational", "name": "BlueCard - TLIF1001 Follow WHS Procedures", "vanity_slug": "bluecard-tlif1001-follow-whs-procedures", "time_to_earn": "Hours", "type_category": "Certification", "show_badge_lmi": false, "show_skill_tag_links": true, "translatable": false, "image": {"id": "2a475222-9978-4a54-b6ec-7b53c691db30", "url": "https://images.credly.com/images/2a475222-9978-4a54-b6ec-7b53c691db30/image.png"}, "image_url": "https://images.credly.com/images/2a475222-9978-4a54-b6ec-7b53c691db30/image.png", "url": "https://www.credly.com/org/teacho/badge/bluecard-tlif1001-follow-whs-procedures", "issuer": {"summary": "issued by TEACHO", "entities": [{"label": "Issued by", "primary": true, "entity": {"type": "Organization", "id": "9f492e43-2452-49f6-bfc3-d8bd5eb23631", "name": "TEACHO", "url": "https://www.credly.com/api/v1/organizations/9f492e43-2452-49f6-bfc3-d8bd5eb23631", "vanity_url": "https://www.credly.com/org/teacho", "internationalize_badge_templates": false, "share_to_ziprecruiter": true, "verified": false}}]}, "alignments": [{"id": "9ab3340b-4f06-4727-aa7c-ae2d8d44bf34", "name": "TLIF1001 - Follow work health and safety procedures", "url": "https://training.gov.au/Training/Details/TLIF1001", "description": null}], "badge_template_activities": [{"id": "415d554c-ecf1-4341-97e6-cbc2626f08f2", "activity_type": "Course", "required_badge_template_id": null, "title": "Complete a BlueCard training course with a TEACHO licensed training provider", "url": "https://bluecard.com.au/providers/"}, {"id": "90d19e96-4c79-4cbc-aade-0a0ad09227fc", "activity_type": "Course", "required_badge_template_id": null, "title": "Attend training every five years to maintain BlueCard currency", "url": null}], "endorsements": [], "skills": [{"id": "64a0b1ae-fc5d-47a4-ae13-58fcb060f9cb", "name": "Adhere To Strict Regulations", "vanity_slug": "adhere-to-strict-regulations"}, {"id": "a220f687-213d-4fec-bd47-6cec90f72775", "name": "Follow Procedures", "vanity_slug": "follow-procedures"}, {"id": "80bf7c7c-a856-46b7-b593-e117b9e13818", "name": "Hazard Identification", "vanity_slug": "hazard-identification"}, {"id": "63dfe078-ea21-4143-9d2b-34c7dd55d074", "name": "Occupational Health and Safety", "vanity_slug": "occupational-health-and-safety"}, {"id": "44c8b992-1925-49d4-80d6-77f4d6dce49e", "name": "OHS", "vanity_slug": "ohs"}, {"id": "a577fcfc-b3a9-4abd-8730-3e8fb1fab687", "name": "Risk Management", "vanity_slug": "risk-management"}, {"id": "ee3dd0b7-4d04-443d-9618-7b506d6a1725", "name": "Teamwork", "vanity_slug": "teamwork"}, {"id": "22b6585c-34ff-44e1-a144-9afe5358ba66", "name": "Use Of PPE", "vanity_slug": "use-of-ppe"}, {"id": "d8c657aa-df01-4270-bd9d-164a97691f4e", "name": "WHS", "vanity_slug": "whs"}, {"id": "1a2a3ff2-6552-4ed1-98ed-08b557759bec", "name": "Work Health And Safety", "vanity_slug": "work-health-and-safety"}]}, "de20df3c-f82f-4c51-8fd9-e34b26816221": {"id": "de20df3c-f82f-4c51-8fd9-e34b26816221", "cost": "Paid", "description": "Earners of this credential have demonstrated the skills and knowledge required to follow work health and safety (WHS)/occupational health and safety (OHS) procedures. Earners are able to identify hazards and control risks, contribute to WHS/OHS management arrangements and complete WHS/OHS records.", "global_activity_url": "https://bluecard.com.au/", "earn_this_badge_url": null, "enable_earn_this_badge": false, "enable_detail_attribute_visibility": true, "level": "Foundational", "name": "BlueCard - TLIF0025 Follow WHS Procedures", "vanity_slug": "bluecard-tlif0025-follow-whs-procedures", "time_to_earn": "Hours", "type_category": "Certification", "show_badge_lmi": false, "show_skill_tag_links": true, "translatable": false, "image": {"id": "ac6d9d13-6863-4011-912b-be62a5b242bb", "url": "https://images.credly.com/images/ac6d9d13-6863-4011-912b-be62a5b242bb/image.png"}, "image_url": "https://images.credly.com/images/ac6d9d13-6863-4011-912b-be62a5b242bb/image.png", "url": "https://www.credly.com/org/teacho/badge/bluecard-tlif0025-follow-whs-procedures", "issuer": {"summary": "issued by TEACHO", "entities": [{"label": "Issued by", "primary": true, "entity": {"type": "Organization", "id": "9f492e43-2452-49f6-bfc3-d8bd5eb23631", "name": "TEACHO", "url": "https://www.credly.com/api/v1/organizations/9f492e43-2452-49f6-bfc3-d8bd5eb23631", "vanity_url": "https://www.credly.com/org/teacho", "internationalize_badge_templates": false, "share_to_ziprecruiter": true, "verified": false}}]}, "alignments": [{"id": "ca022a3c-df75-4fa3-b838-9c0fdfaa7a3b", "name": "TLIF0025 - Follow work health and safety procedures", "url": "https://training.gov.au/Training/Details/TLIF0025", "description": null}], "badge_template_activities": [{"id": "9904b922-743b-46c8-86ac-d308b5a74983", "activity_type": "Course", "required_badge_template_id": null, "title": "Complete a BlueCard training course with a TEACHO licensed training provider", "url": "https://bluecard.com.au/providers/"}, {"id": "9028c7e7-69cf-46c1-b27e-421797db3edd", "activity_type": "Course", "required_badge_template_id": null, "title": "Attend training every five years to maintain BlueCard currency", "url": null}], "endorsements": [], "skills": [{"id": "64a0b1ae-fc5d-47a4-ae13-58fcb060f9cb", "name": "Adhere To Strict Regulations", "vanity_slug": "adhere-to-strict-regulations"}, {"id": "a220f687-213d-4fec-bd47-6cec90f72775", "name": "Follow Procedures", "vanity_slug": "follow-procedures"}, {"id": "80bf7c7c-a856-46b7-b593-e117b9e13818", "name": "Hazard Identification", "vanity_slug": "hazard-identification"}, {"id": "63dfe078-ea21-4143-9d2b-34c7dd55d074", "name": "Occupational Health and Safety", "vanity_slug": "occupational-health-and-safety"}, {"id": "44c8b992-1925-49d4-80d6-77f4d6dce49e", "name": "OHS", "vanity_slug": "ohs"}, {"id": "a577fcfc-b3a9-4abd-8730-3e8fb1fab687", "name": "Risk Management", "vanity_slug": "risk-management"}, {"id": "ee3dd0b7-4d04-443d-9618-7b506d6a1725", "name": "Teamwork", "vanity_slug": "teamwork"}, {"id": "22b6585c-34ff-44e1-a144-9afe5358ba66", "name": "Use Of PPE", "vanity_slug": "use-of-ppe"}, {"id": "d8c657aa-df01-4270-bd9d-164a97691f4e", "name": "WHS", "vanity_slug": "whs"}, {"id": "1a2a3ff2-6552-4ed1-98ed-08b557759bec", "name": "Work Health And Safety", "vanity_slug": "work-health-and-safety"}]}, "f36e57d3-2bd3-407c-aa20-17fabe03cbdb": {"id": "f36e57d3-2bd3-407c-aa20-17fabe03cbdb", "cost": "Paid", "description": "Earners of this credential have demonstrated the skills and knowledge required to follow and apply work health and safety (WHS) / occupational health and safety (OHS) procedures when carrying out work in compliance with the relevant WHS/OHS regulations. Earners are able to identify hazards and control risks, contribute to WHS/OHS management arrangements and complete WHS/OHS records. This Unit of competency was deleted and replaced by TLIF107C Follow OHS Procedures, in 2007.", "global_activity_url": "https://www.bluecard.com.au", "earn_this_badge_url": null, "enable_earn_this_badge": false, "enable_detail_attribute_visibility": true, "level": "Foundational", "name": "BlueCard - TDTF197B Follow OHS Procedures", "vanity_slug": "bluecard-tdtf197b-follow-ohs-procedures", "time_to_earn": "Hours", "type_category": "Certification", "show_badge_lmi": false, "show_skill_tag_links": true, "translatable": false, "image": {"id": "569f0403-8626-44fd-8355-017225a25fdd", "url": "https://images.credly.com/images/569f0403-8626-44fd-8355-017225a25fdd/TEACHO-TDTF197B.png"}, "image_url": "https://images.credly.com/images/569f0403-8626-44fd-8355-017225a25fdd/TEACHO-TDTF197B.png", "url": "https://www.credly.com/org/teacho/badge/bluecard-tdtf197b-follow-ohs-procedures", "issuer": {"summary": "issued by TEACHO", "entities": [{"label": "Issued by", "primary": true, "entity": {"type": "Organization", "id": "9f492e43-2452-49f6-bfc3-d8bd5eb23631", "name": "TEACHO", "url": "https://www.credly.com/api/v1/organizations/9f492e43-2452-49f6-bfc3-d8bd5eb23631", "vanity_url": "https://www.credly.com/org/teacho", "internationalize_badge_templates": false, "share_to_ziprecruiter": true, "verified": false}}]}, "alignments": [{"id": "9c638ea4-3ac7-483c-b6e9-3e934a7746c8", "name": "TDTF197B - Follow OHS Procedures (Deleted)", "url": "https://training.gov.au/Training/Details/TDTF197B", "description": null}], "badge_template_activities": [{"id": "04de22e4-3f7e-4858-b023-d7c930f577db", "activity_type": "Course", "required_badge_template_id": null, "title": "Complete a BlueCard training course with a TEACHO licensed training provider", "url": "https://bluecard.com.au/providers/"}, {"id": "de93cb8b-89a5-4d0b-b62f-282bcf701aa3", "activity_type": "Course", "required_badge_template_id": null, "title": "Attend training every five years to maintain BlueCard currency", "url": null}], "endorsements": [], "skills": [{"id": "64a0b1ae-fc5d-47a4-ae13-58fcb060f9cb", "name": "Adhere To Strict Regulations", "vanity_slug": "adhere-to-strict-regulations"}, {"id": "a220f687-213d-4fec-bd47-6cec90f72775", "name": "Follow Procedures", "vanity_slug": "follow-procedures"}, {"id": "80bf7c7c-a856-46b7-b593-e117b9e13818", "name": "Hazard Identification", "vanity_slug": "hazard-identification"}, {"id": "63dfe078-ea21-4143-9d2b-34c7dd55d074", "name": "Occupational Health and Safety", "vanity_slug": "occupational-health-and-safety"}, {"id": "44c8b992-1925-49d4-80d6-77f4d6dce49e", "name": "OHS", "vanity_slug": "ohs"}, {"id": "a577fcfc-b3a9-4abd-8730-3e8fb1fab687", "name": "Risk Management", "vanity_slug": "risk-management"}, {"id": "ee3dd0b7-4d04-443d-9618-7b506d6a1725", "name": "Teamwork", "vanity_slug": "teamwork"}, {"id": "22b6585c-34ff-44e1-a144-9afe5358ba66", "name": "Use Of PPE", "vanity_slug": "use-of-ppe"}, {"id": "d8c657aa-df01-4270-bd9d-164a97691f4e", "name": "WHS", "vanity_slug": "whs"}, {"id": "1a2a3ff2-6552-4ed1-98ed-08b557759bec", "name": "Work Health And Safety", "vanity_slug": "work-health-and-safety"}]}, "98ff8f75-8af3-4fab-87cb-cf046a24e08c": {"id": "98ff8f75-8af3-4fab-87cb-cf046a24e08c", "cost": "Paid", "description": "Earners of this credential have demonstrated the skills and knowledge required to follow and apply work health and safety (WHS) / occupational health and safety (OHS) procedures when carrying out work in compliance with the relevant WHS/OHS regulations. Earners are able to identify hazards and control risks, contribute to WHS/OHS management arrangements and complete WHS/OHS records. This competency was superseded on 6 Mar 2011.", "global_activity_url": "https://www.bluecard.com.au", "earn_this_badge_url": null, "enable_earn_this_badge": false, "enable_detail_attribute_visibility": true, "level": "Foundational", "name": "BlueCard - TLIF107C Follow OHS Procedures", "vanity_slug": "bluecard-tlif107c-follow-ohs-procedures", "time_to_earn": "Hours", "type_category": "Certification", "show_badge_lmi": false, "show_skill_tag_links": true, "translatable": false, "image": {"id": "880231d0-9720-4a52-8a23-176732c57c91", "url": "https://images.credly.com/images/880231d0-9720-4a52-8a23-176732c57c91/TEACHO-TLIF107C.png"}, "image_url": "https://images.credly.com/images/880231d0-9720-4a52-8a23-176732c57c91/TEACHO-TLIF107C.png", "url": "https://www.credly.com/org/teacho/badge/bluecard-tlif107c-follow-ohs-procedures", "issuer": {"summary": "issued by TEACHO", "entities": [{"label": "Issued by", "primary": true, "entity": {"type": "Organization", "id": "9f492e43-2452-49f6-bfc3-d8bd5eb23631", "name": "TEACHO", "url": "https://www.credly.com/api/v1/organizations/9f492e43-2452-49f6-bfc3-d8bd5eb23631", "vanity_url": "https://www.credly.com/org/teacho", "internationalize_badge_templates": false, "share_to_ziprecruiter": true, "verified": false}}]}, "alignments": [{"id": "d9ec9a89-e727-43d6-99d9-ae042f194567", "name": "TLIF107C - Follow OHS Procedures (Superseded)", "url": "https://training.gov.au/Training/Details/TLIF107C", "description": null}], "badge_template_activities": [{"id": "ca6ecfd8-0439-4d4a-b9e2-2b48f71c617b", "activity_type": "Course", "required_badge_template_id": null, "title": "Complete a BlueCard training course with a TEACHO licensed training provider", "url": "https://bluecard.com.au/providers/"}, {"id": "c5f6f75f-9709-4e95-b476-8d77817ece79", "activity_type": "Course", "required_badge_template_id": null, "title": "Attend training every five years to maintain BlueCard currency", "url": null}], "endorsements": [], "skills": [{"id": "64a0b1ae-fc5d-47a4-ae13-58fcb060f9cb", "name": "Adhere To Strict Regulations", "vanity_slug": "adhere-to-strict-regulations"}, {"id": "a220f687-213d-4fec-bd47-6cec90f72775", "name": "Follow Procedures", "vanity_slug": "follow-procedures"}, {"id": "80bf7c7c-a856-46b7-b593-e117b9e13818", "name": "Hazard Identification", "vanity_slug": "hazard-identification"}, {"id": "63dfe078-ea21-4143-9d2b-34c7dd55d074", "name": "Occupational Health and Safety", "vanity_slug": "occupational-health-and-safety"}, {"id": "44c8b992-1925-49d4-80d6-77f4d6dce49e", "name": "OHS", "vanity_slug": "ohs"}, {"id": "a577fcfc-b3a9-4abd-8730-3e8fb1fab687", "name": "Risk Management", "vanity_slug": "risk-management"}, {"id": "ee3dd0b7-4d04-443d-9618-7b506d6a1725", "name": "Teamwork", "vanity_slug": "teamwork"}, {"id": "22b6585c-34ff-44e1-a144-9afe5358ba66", "name": "Use Of PPE", "vanity_slug": "use-of-ppe"}, {"id": "d8c657aa-df01-4270-bd9d-164a97691f4e", "name": "WHS", "vanity_slug": "whs"}, {"id": "1a2a3ff2-6552-4ed1-98ed-08b557759bec", "name": "Work Health And Safety", "vanity_slug": "work-health-and-safety"}]}, "29f99c58-b256-4e68-87cb-715a394c86ba": {"id": "29f99c58-b256-4e68-87cb-715a394c86ba", "cost": "Paid", "description": "Earners of this credential have demonstrated the skills and knowledge required to follow and apply work health and safety (WHS) / occupational health and safety (OHS) procedures when carrying out work in compliance with the relevant WHS/OHS regulations. Earners are able to identify hazards and control risks, contribute to WHS/OHS management arrangements and complete WHS/OHS records. This competency was superseded by TLIF1001 Follow Work Health and Safety procedures on 18 Oct 2015.", "global_activity_url": "https://www.bluecard.com.au", "earn_this_badge_url": null, "enable_earn_this_badge": false, "enable_detail_attribute_visibility": true, "level": "Foundational", "name": "BlueCard - TLIF1001A Follow OHS Procedures", "vanity_slug": "bluecard-tlif1001a-follow-ohs-procedures", "time_to_earn": "Hours", "type_category": "Certification", "show_badge_lmi": false, "show_skill_tag_links": true, "translatable": false, "image": {"id": "4cd74b55-5e9a-41cf-8e48-5709d118be2b", "url": "https://images.credly.com/images/4cd74b55-5e9a-41cf-8e48-5709d118be2b/TEACHO-TLIF1001A.png"}, "image_url": "https://images.credly.com/images/4cd74b55-5e9a-41cf-8e48-5709d118be2b/TEACHO-TLIF1001A.png", "url": "https://www.credly.com/org/teacho/badge/bluecard-tlif1001a-follow-ohs-procedures", "issuer": {"summary": "issued by TEACHO", "entities": [{"label": "Issued by", "primary": true, "entity": {"type": "Organization", "id": "9f492e43-2452-49f6-bfc3-d8bd5eb23631", "name": "TEACHO", "url": "https://www.credly.com/api/v1/organizations/9f492e43-2452-49f6-bfc3-d8bd5eb23631", "vanity_url": "https://www.credly.com/org/teacho", "internationalize_badge_templates": false, "share_to_ziprecruiter": true, "verified": false}}]}, "alignments": [{"id": "d0915e29-d070-4d60-8093-348d95ed5438", "name": "TLIF1001A - Follow OHS Procedures (Superseded)", "url": "https://training.gov.au/Training/Details/TLIF1001A", "description": null}], "badge_template_activities": [{"id": "22bfa56f-e8af-45ed-a840-2cddce22cf35", "activity_type": "Course", "required_badge_template_id": null, "title": "Complete a BlueCard training course with a TEACHO licensed training provider", "url": "https://bluecard.com.au/providers/"}, {"id": "e664a7eb-6a4a-41cd-9383-b558f2afb5f0", "activity_type": "Course", "required_badge_template_id": null, "title": "Attend training every five years to maintain BlueCard currency", "url": null}], "endorsements": [], "skills": [{"id": "64a0b1ae-fc5d-47a4-ae13-58fcb060f9cb", "name": "Adhere To Strict Regulations", "vanity_slug": "adhere-to-strict-regulations"}, {"id": "a220f687-213d-4fec-bd47-6cec90f72775", "name": "Follow Procedures", "vanity_slug": "follow-procedures"}, {"id": "80bf7c7c-a856-46b7-b593-e117b9e13818", "name": "Hazard Identification", "vanity_slug": "hazard-identification"}, {"id": "63dfe078-ea21-4143-9d2b-34c7dd55d074", "name": "Occupational Health and Safety", "vanity_slug": "occupational-health-and-safety"}, {"id": "44c8b992-1925-49d4-80d6-77f4d6dce49e", "name": "OHS", "vanity_slug": "ohs"}, {"id": "a577fcfc-b3a9-4abd-8730-3e8fb1fab687", "name": "Risk Management", "vanity_slug": "risk-management"}, {"id": "ee3dd0b7-4d04-443d-9618-7b506d6a1725", "name": "Teamwork", "vanity_slug": "teamwork"}, {"id": "22b6585c-34ff-44e1-a144-9afe5358ba66", "name": "Use Of PPE", "vanity_slug": "use-of-ppe"}, {"id": "d8c657aa-df01-4270-bd9d-164a97691f4e", "name": "WHS", "vanity_slug": "whs"}, {"id": "1a2a3ff2-6552-4ed1-98ed-08b557759bec", "name": "Work Health And Safety", "vanity_slug": "work-health-and-safety"}]}}